dlts-0.0.2.post4.dist-info/METADATA
dlts-0.0.2.post4.dist-info/WHEEL
dlts-0.0.2.post4.dist-info/entry_points.txt
dlts-0.0.2.post4.dist-info/licenses/LICENSE
dlts/__init__.py
dlts/config/__init__.py
dlts/config/base_config.py
dlts/config/ehfr_net.py
dlts/layers/__init__.py
dlts/layers/norm_layer.py
dlts/layers/pool_layer.py
dlts/models/__init__.py
dlts/models/ehfr_net.py
dlts/modules/__init__.py
dlts/modules/h_block.py
dlts/modules/inverted_residual.py
dlts/modules/lp_vit.py
dlts/utils/__init__.py
dlts/utils/_registry.py
dlts/utils/math_utils.py
dlts/version.py
dlts-0.0.2.post4.dist-info/RECORD
