Metadata-Version: 2.1
Name: dlts
Version: 0.0.2.post4
Summary: Deep Learning Tools for Pytorch
Keywords: python,tools,model
Author-Email: Ian Zhu <IanZhu@m.ldu.edu.cn>
License: MIT
Project-URL: homepage, https://github.com/10-4zz/model_tools
Project-URL: repository, https://github.com/10-4zz/model_tools
Requires-Python: >=3.8
Requires-Dist: torch
Requires-Dist: torchvision
Requires-Dist: model_logger_dp
